{"cameraMode":{"drawMode":0,"name":"Shaded","section":"Shading Mode"},"sceneLighting":true,"audioPlay":false,"sceneViewState":{"showFog":true,"showMaterialUpdate":false,"showSkybox":true,"showFlares":true,"showImageEffects":true,"showParticleSystems":true},"in2DMode":false,"pivot":{"x":0.48835164308547976,"y":-0.4186394214630127,"z":4.202281951904297},"rotation":{"x":-0.15853725373744965,"y":-0.0349472314119339,"z":0.0056150443851947788,"w":-0.9867185950279236},"size":13.608617782592774,"orthographic":false}